[
  {
    "video": "\/data\/upload\/1\/cfa0b5cb-VPI-28.mp4",
    "id": 2,
    "box": [
      {
        "framesCount": 5355,
        "duration": 178.5,
        "sequence": [
          {
            "frame": 1,
            "enabled": true,
            "rotation": 0,
            "x": 22.783389450055793,
            "y": 0.11846863698716623,
            "width": 55.33108866442189,
            "height": 99.1644843496695,
            "time": 0.03333333333333333
          },
          {
            "x": 22.783389450055793,
            "y": 0.11846863698716623,
            "width": 55.33108866442189,
            "height": 99.1644843496695,
            "rotation": 0,
            "enabled": false,
            "frame": 5,
            "time": 0.16666666666666666
          },
          {
            "x": 22.783389450055793,
            "y": 0.11846863698716623,
            "width": 55.33108866442189,
            "height": 99.1644843496695,
            "rotation": 0,
            "enabled": true,
            "frame": 121,
            "time": 4.033333333333333
          },
          {
            "x": 22.783389450055793,
            "y": 0.11846863698716623,
            "width": 55.33108866442189,
            "height": 99.1644843496695,
            "rotation": 0,
            "enabled": false,
            "frame": 463,
            "time": 15.433333333333334
          },
          {
            "x": 22.783389450055793,
            "y": 0.11846863698716623,
            "width": 55.33108866442189,
            "height": 99.1644843496695,
            "rotation": 0,
            "enabled": true,
            "frame": 490,
            "time": 16.333333333333332
          },
          {
            "x": 22.783389450055793,
            "y": 0.11846863698716623,
            "width": 55.33108866442189,
            "height": 99.1644843496695,
            "rotation": 0,
            "enabled": false,
            "frame": 586,
            "time": 19.533333333333335
          },
          {
            "x": 22.783389450055793,
            "y": 0.11846863698716623,
            "width": 55.33108866442189,
            "height": 99.1644843496695,
            "rotation": 0,
            "enabled": true,
            "frame": 666,
            "time": 22.2
          },
          {
            "x": 22.783389450055793,
            "y": 0.11846863698716623,
            "width": 55.33108866442189,
            "height": 99.1644843496695,
            "rotation": 0,
            "enabled": false,
            "frame": 755,
            "time": 25.166666666666668
          },
          {
            "x": 22.783389450055793,
            "y": 0.11846863698716623,
            "width": 55.33108866442189,
            "height": 99.1644843496695,
            "rotation": 0,
            "enabled": true,
            "frame": 816,
            "time": 27.2
          },
          {
            "x": 22.783389450055793,
            "y": 0.11846863698716623,
            "width": 55.33108866442189,
            "height": 99.1644843496695,
            "rotation": 0,
            "enabled": false,
            "frame": 932,
            "time": 31.066666666666666
          },
          {
            "x": 22.783389450055793,
            "y": 0.11846863698716623,
            "width": 55.33108866442189,
            "height": 99.1644843496695,
            "rotation": 0,
            "enabled": true,
            "frame": 1011,
            "time": 33.7
          },
          {
            "x": 22.783389450055793,
            "y": 0.11846863698716623,
            "width": 55.33108866442189,
            "height": 99.1644843496695,
            "rotation": 0,
            "enabled": false,
            "frame": 1112,
            "time": 37.06666666666667
          },
          {
            "x": 22.783389450055793,
            "y": 0.11846863698716623,
            "width": 55.33108866442189,
            "height": 99.1644843496695,
            "rotation": 0,
            "enabled": true,
            "frame": 1170,
            "time": 39
          },
          {
            "x": 22.783389450055793,
            "y": 0.11846863698716623,
            "width": 55.33108866442189,
            "height": 99.1644843496695,
            "rotation": 0,
            "enabled": false,
            "frame": 1547,
            "time": 51.56666666666667
          },
          {
            "x": 22.783389450055793,
            "y": 0.11846863698716623,
            "width": 55.33108866442189,
            "height": 99.1644843496695,
            "rotation": 0,
            "enabled": true,
            "frame": 1566,
            "time": 52.2
          },
          {
            "x": 22.783389450055793,
            "y": 0.11846863698716623,
            "width": 55.33108866442189,
            "height": 99.1644843496695,
            "rotation": 0,
            "enabled": false,
            "frame": 1572,
            "time": 52.4
          },
          {
            "x": 22.783389450055793,
            "y": 0.11846863698716623,
            "width": 55.33108866442189,
            "height": 99.1644843496695,
            "rotation": 0,
            "enabled": true,
            "frame": 1976,
            "time": 65.86666666666666
          },
          {
            "x": 22.783389450055793,
            "y": 0.11846863698716623,
            "width": 55.33108866442189,
            "height": 99.1644843496695,
            "rotation": 0,
            "enabled": false,
            "frame": 2426,
            "time": 80.86666666666666
          },
          {
            "x": 22.783389450055793,
            "y": 0.11846863698716623,
            "width": 55.33108866442189,
            "height": 99.1644843496695,
            "rotation": 0,
            "enabled": true,
            "frame": 2822,
            "time": 94.06666666666666
          },
          {
            "x": 22.783389450055793,
            "y": 0.11846863698716623,
            "width": 55.33108866442189,
            "height": 99.1644843496695,
            "rotation": 0,
            "enabled": false,
            "frame": 3109,
            "time": 103.63333333333334
          },
          {
            "x": 22.783389450055793,
            "y": 0.11846863698716623,
            "width": 55.33108866442189,
            "height": 99.1644843496695,
            "rotation": 0,
            "enabled": true,
            "frame": 3565,
            "time": 118.83333333333333
          },
          {
            "x": 22.783389450055793,
            "y": 0.11846863698716623,
            "width": 55.33108866442189,
            "height": 99.1644843496695,
            "rotation": 0,
            "enabled": false,
            "frame": 3763,
            "time": 125.43333333333334
          },
          {
            "x": 22.783389450055793,
            "y": 0.11846863698716623,
            "width": 55.33108866442189,
            "height": 99.1644843496695,
            "rotation": 0,
            "enabled": true,
            "frame": 3907,
            "time": 130.23333333333332
          },
          {
            "x": 22.783389450055793,
            "y": 0.11846863698716623,
            "width": 55.33108866442189,
            "height": 99.1644843496695,
            "rotation": 0,
            "enabled": false,
            "frame": 4060,
            "time": 135.33333333333334
          },
          {
            "x": 22.783389450055793,
            "y": 0.11846863698716623,
            "width": 55.33108866442189,
            "height": 99.1644843496695,
            "rotation": 0,
            "enabled": true,
            "frame": 4117,
            "time": 137.23333333333332
          },
          {
            "x": 22.783389450055793,
            "y": 0.11846863698716623,
            "width": 55.33108866442189,
            "height": 99.1644843496695,
            "rotation": 0,
            "enabled": false,
            "frame": 4276,
            "time": 142.53333333333333
          },
          {
            "x": 22.783389450055793,
            "y": 0.11846863698716623,
            "width": 55.33108866442189,
            "height": 99.1644843496695,
            "rotation": 0,
            "enabled": true,
            "frame": 4348,
            "time": 144.93333333333334
          },
          {
            "x": 22.783389450055793,
            "y": 0.11846863698716623,
            "width": 55.33108866442189,
            "height": 99.1644843496695,
            "rotation": 0,
            "enabled": false,
            "frame": 4453,
            "time": 148.43333333333334
          },
          {
            "x": 22.783389450055793,
            "y": 0.11846863698716623,
            "width": 55.33108866442189,
            "height": 99.1644843496695,
            "rotation": 0,
            "enabled": true,
            "frame": 4523,
            "time": 150.76666666666668
          },
          {
            "x": 22.783389450055793,
            "y": 0.11846863698716623,
            "width": 55.33108866442189,
            "height": 99.1644843496695,
            "rotation": 0,
            "enabled": false,
            "frame": 4951,
            "time": 165.03333333333333
          },
          {
            "x": 22.783389450055793,
            "y": 0.11846863698716623,
            "width": 55.33108866442189,
            "height": 99.1644843496695,
            "rotation": 0,
            "enabled": true,
            "frame": 5002,
            "time": 166.73333333333332
          },
          {
            "x": 22.783389450055793,
            "y": 0.11846863698716623,
            "width": 55.33108866442189,
            "height": 99.1644843496695,
            "rotation": 0,
            "enabled": false,
            "frame": 5113,
            "time": 170.43333333333334
          },
          {
            "x": 22.783389450055793,
            "y": 0.11846863698716623,
            "width": 55.33108866442189,
            "height": 99.1644843496695,
            "rotation": 0,
            "enabled": true,
            "frame": 5157,
            "time": 171.9
          },
          {
            "x": 22.783389450055793,
            "y": 0.11846863698716623,
            "width": 55.33108866442189,
            "height": 99.1644843496695,
            "rotation": 0,
            "enabled": false,
            "frame": 5184,
            "time": 172.8
          },
          {
            "x": 22.783389450055793,
            "y": 0.11846863698716623,
            "width": 55.33108866442189,
            "height": 99.1644843496695,
            "rotation": 0,
            "enabled": true,
            "frame": 5218,
            "time": 173.93333333333334
          }
        ],
        "labels": [
          "Negative"
        ]
      },
      {
        "framesCount": 5355,
        "duration": 178.5,
        "sequence": [
          {
            "frame": 6,
            "enabled": true,
            "rotation": 0,
            "x": 23.007856341189594,
            "y": 0.11846863698718565,
            "width": 54.882154882154644,
            "height": 98.96495822421738,
            "time": 0.2
          },
          {
            "x": 23.007856341189594,
            "y": 0.11846863698718565,
            "width": 54.882154882154644,
            "height": 98.96495822421738,
            "rotation": 0,
            "enabled": false,
            "frame": 120,
            "time": 4
          },
          {
            "x": 23.007856341189594,
            "y": 0.11846863698718565,
            "width": 54.882154882154644,
            "height": 98.96495822421738,
            "rotation": 0,
            "enabled": true,
            "frame": 464,
            "time": 15.466666666666667
          },
          {
            "x": 23.007856341189594,
            "y": 0.11846863698718565,
            "width": 54.882154882154644,
            "height": 98.96495822421738,
            "rotation": 0,
            "enabled": false,
            "frame": 489,
            "time": 16.3
          },
          {
            "x": 23.007856341189594,
            "y": 0.11846863698718565,
            "width": 54.882154882154644,
            "height": 98.96495822421738,
            "rotation": 0,
            "enabled": true,
            "frame": 587,
            "time": 19.566666666666666
          },
          {
            "x": 23.007856341189594,
            "y": 0.11846863698718565,
            "width": 54.882154882154644,
            "height": 98.96495822421738,
            "rotation": 0,
            "enabled": false,
            "frame": 665,
            "time": 22.166666666666668
          },
          {
            "x": 23.007856341189594,
            "y": 0.11846863698718565,
            "width": 54.882154882154644,
            "height": 98.96495822421738,
            "rotation": 0,
            "enabled": true,
            "frame": 756,
            "time": 25.2
          },
          {
            "x": 23.007856341189594,
            "y": 0.11846863698718565,
            "width": 54.882154882154644,
            "height": 98.96495822421738,
            "rotation": 0,
            "enabled": false,
            "frame": 815,
            "time": 27.166666666666668
          },
          {
            "x": 23.007856341189594,
            "y": 0.11846863698718565,
            "width": 54.882154882154644,
            "height": 98.96495822421738,
            "rotation": 0,
            "enabled": true,
            "frame": 933,
            "time": 31.1
          },
          {
            "x": 23.007856341189594,
            "y": 0.11846863698718565,
            "width": 54.882154882154644,
            "height": 98.96495822421738,
            "rotation": 0,
            "enabled": false,
            "frame": 1010,
            "time": 33.666666666666664
          },
          {
            "x": 23.007856341189594,
            "y": 0.11846863698718565,
            "width": 54.882154882154644,
            "height": 98.96495822421738,
            "rotation": 0,
            "enabled": true,
            "frame": 1113,
            "time": 37.1
          },
          {
            "x": 23.007856341189594,
            "y": 0.11846863698718565,
            "width": 54.882154882154644,
            "height": 98.96495822421738,
            "rotation": 0,
            "enabled": false,
            "frame": 1169,
            "time": 38.96666666666667
          },
          {
            "x": 23.007856341189594,
            "y": 0.11846863698718565,
            "width": 54.882154882154644,
            "height": 98.96495822421738,
            "rotation": 0,
            "enabled": true,
            "frame": 1548,
            "time": 51.6
          },
          {
            "x": 23.007856341189594,
            "y": 0.11846863698718565,
            "width": 54.882154882154644,
            "height": 98.96495822421738,
            "rotation": 0,
            "enabled": false,
            "frame": 1565,
            "time": 52.166666666666664
          },
          {
            "x": 23.007856341189594,
            "y": 0.11846863698718565,
            "width": 54.882154882154644,
            "height": 98.96495822421738,
            "rotation": 0,
            "enabled": true,
            "frame": 1573,
            "time": 52.43333333333333
          },
          {
            "x": 23.007856341189594,
            "y": 0.11846863698718565,
            "width": 54.882154882154644,
            "height": 98.96495822421738,
            "rotation": 0,
            "enabled": false,
            "frame": 1975,
            "time": 65.83333333333333
          },
          {
            "x": 23.007856341189594,
            "y": 0.11846863698718565,
            "width": 54.882154882154644,
            "height": 98.96495822421738,
            "rotation": 0,
            "enabled": true,
            "frame": 2427,
            "time": 80.9
          },
          {
            "x": 23.007856341189594,
            "y": 0.11846863698718565,
            "width": 54.882154882154644,
            "height": 98.96495822421738,
            "rotation": 0,
            "enabled": false,
            "frame": 2821,
            "time": 94.03333333333333
          },
          {
            "x": 23.007856341189594,
            "y": 0.11846863698718565,
            "width": 54.882154882154644,
            "height": 98.96495822421738,
            "rotation": 0,
            "enabled": true,
            "frame": 3110,
            "time": 103.66666666666667
          },
          {
            "x": 23.007856341189594,
            "y": 0.11846863698718565,
            "width": 54.882154882154644,
            "height": 98.96495822421738,
            "rotation": 0,
            "enabled": false,
            "frame": 3564,
            "time": 118.8
          },
          {
            "x": 23.007856341189594,
            "y": 0.11846863698718565,
            "width": 54.882154882154644,
            "height": 98.96495822421738,
            "rotation": 0,
            "enabled": true,
            "frame": 3764,
            "time": 125.46666666666667
          },
          {
            "x": 23.007856341189594,
            "y": 0.11846863698718565,
            "width": 54.882154882154644,
            "height": 98.96495822421738,
            "rotation": 0,
            "enabled": false,
            "frame": 3906,
            "time": 130.2
          },
          {
            "x": 23.007856341189594,
            "y": 0.11846863698718565,
            "width": 54.882154882154644,
            "height": 98.96495822421738,
            "rotation": 0,
            "enabled": true,
            "frame": 4061,
            "time": 135.36666666666667
          },
          {
            "x": 23.007856341189594,
            "y": 0.11846863698718565,
            "width": 54.882154882154644,
            "height": 98.96495822421738,
            "rotation": 0,
            "enabled": false,
            "frame": 4116,
            "time": 137.2
          },
          {
            "x": 23.007856341189594,
            "y": 0.11846863698718565,
            "width": 54.882154882154644,
            "height": 98.96495822421738,
            "rotation": 0,
            "enabled": true,
            "frame": 4277,
            "time": 142.56666666666666
          },
          {
            "x": 23.007856341189594,
            "y": 0.11846863698718565,
            "width": 54.882154882154644,
            "height": 98.96495822421738,
            "rotation": 0,
            "enabled": false,
            "frame": 4347,
            "time": 144.9
          },
          {
            "x": 23.007856341189594,
            "y": 0.11846863698718565,
            "width": 54.882154882154644,
            "height": 98.96495822421738,
            "rotation": 0,
            "enabled": true,
            "frame": 4454,
            "time": 148.46666666666667
          },
          {
            "x": 23.007856341189594,
            "y": 0.11846863698718565,
            "width": 54.882154882154644,
            "height": 98.96495822421738,
            "rotation": 0,
            "enabled": false,
            "frame": 4522,
            "time": 150.73333333333332
          },
          {
            "x": 23.007856341189594,
            "y": 0.11846863698718565,
            "width": 54.882154882154644,
            "height": 98.96495822421738,
            "rotation": 0,
            "enabled": true,
            "frame": 4952,
            "time": 165.06666666666666
          },
          {
            "x": 23.007856341189594,
            "y": 0.11846863698718565,
            "width": 54.882154882154644,
            "height": 98.96495822421738,
            "rotation": 0,
            "enabled": false,
            "frame": 5001,
            "time": 166.7
          },
          {
            "x": 23.007856341189594,
            "y": 0.11846863698718565,
            "width": 54.882154882154644,
            "height": 98.96495822421738,
            "rotation": 0,
            "enabled": true,
            "frame": 5114,
            "time": 170.46666666666667
          },
          {
            "x": 23.007856341189594,
            "y": 0.11846863698718565,
            "width": 54.882154882154644,
            "height": 98.96495822421738,
            "rotation": 0,
            "enabled": false,
            "frame": 5156,
            "time": 171.86666666666667
          },
          {
            "x": 23.007856341189594,
            "y": 0.11846863698718565,
            "width": 54.882154882154644,
            "height": 98.96495822421738,
            "rotation": 0,
            "enabled": true,
            "frame": 5185,
            "time": 172.83333333333334
          },
          {
            "x": 23.007856341189594,
            "y": 0.11846863698718565,
            "width": 54.882154882154644,
            "height": 98.96495822421738,
            "rotation": 0,
            "enabled": false,
            "frame": 5217,
            "time": 173.9
          }
        ],
        "labels": [
          "Positive"
        ]
      }
    ],
    "annotator": 1,
    "annotation_id": 1,
    "created_at": "2024-09-22T06:39:21.678460Z",
    "updated_at": "2024-09-22T06:39:21.678473Z",
    "lead_time": 1952.851
  },
  {
    "video": "\/data\/upload\/1\/28ce1334-VPI-29.mp4",
    "id": 3,
    "box": [
      {
        "framesCount": 3964,
        "duration": 132.133,
        "sequence": [
          {
            "frame": 1,
            "enabled": true,
            "rotation": 0,
            "x": 23.14062499999986,
            "y": 0.16666666666666402,
            "width": 54.562499999999595,
            "height": 98.99999999999936,
            "time": 0.03333333333333333
          },
          {
            "x": 23.14062499999986,
            "y": 0.16666666666666402,
            "width": 54.562499999999595,
            "height": 98.99999999999936,
            "rotation": 0,
            "enabled": false,
            "frame": 359,
            "time": 11.966666666666667
          },
          {
            "x": 23.14062499999986,
            "y": 0.16666666666666402,
            "width": 54.562499999999595,
            "height": 98.99999999999936,
            "rotation": 0,
            "enabled": true,
            "frame": 440,
            "time": 14.666666666666666
          },
          {
            "x": 23.14062499999986,
            "y": 0.16666666666666402,
            "width": 54.562499999999595,
            "height": 98.99999999999936,
            "rotation": 0,
            "enabled": false,
            "frame": 571,
            "time": 19.033333333333335
          },
          {
            "x": 23.14062499999986,
            "y": 0.16666666666666402,
            "width": 54.562499999999595,
            "height": 98.99999999999936,
            "rotation": 0,
            "enabled": true,
            "frame": 676,
            "time": 22.533333333333335
          },
          {
            "x": 23.14062499999986,
            "y": 0.16666666666666402,
            "width": 54.562499999999595,
            "height": 98.99999999999936,
            "rotation": 0,
            "enabled": false,
            "frame": 770,
            "time": 25.666666666666668
          },
          {
            "x": 23.14062499999986,
            "y": 0.16666666666666402,
            "width": 54.562499999999595,
            "height": 98.99999999999936,
            "rotation": 0,
            "enabled": true,
            "frame": 834,
            "time": 27.8
          },
          {
            "x": 23.14062499999986,
            "y": 0.16666666666666402,
            "width": 54.562499999999595,
            "height": 98.99999999999936,
            "rotation": 0,
            "enabled": false,
            "frame": 992,
            "time": 33.06666666666667
          },
          {
            "x": 23.14062499999986,
            "y": 0.16666666666666402,
            "width": 54.562499999999595,
            "height": 98.99999999999936,
            "rotation": 0,
            "enabled": true,
            "frame": 1483,
            "time": 49.43333333333333
          },
          {
            "x": 23.14062499999986,
            "y": 0.16666666666666402,
            "width": 54.562499999999595,
            "height": 98.99999999999936,
            "rotation": 0,
            "enabled": false,
            "frame": 1602,
            "time": 53.4
          },
          {
            "x": 23.14062499999986,
            "y": 0.16666666666666402,
            "width": 54.562499999999595,
            "height": 98.99999999999936,
            "rotation": 0,
            "enabled": true,
            "frame": 2092,
            "time": 69.73333333333333
          },
          {
            "x": 23.14062499999986,
            "y": 0.16666666666666402,
            "width": 54.562499999999595,
            "height": 98.99999999999936,
            "rotation": 0,
            "enabled": false,
            "frame": 3413,
            "time": 113.76666666666667
          },
          {
            "x": 23.14062499999986,
            "y": 0.16666666666666402,
            "width": 54.562499999999595,
            "height": 98.99999999999936,
            "rotation": 0,
            "enabled": true,
            "frame": 3482,
            "time": 116.06666666666666
          },
          {
            "x": 23.14062499999986,
            "y": 0.16666666666666402,
            "width": 54.562499999999595,
            "height": 98.99999999999936,
            "rotation": 0,
            "enabled": false,
            "frame": 3534,
            "time": 117.8
          },
          {
            "x": 23.14062499999986,
            "y": 0.16666666666666402,
            "width": 54.562499999999595,
            "height": 98.99999999999936,
            "rotation": 0,
            "enabled": true,
            "frame": 3634,
            "time": 121.13333333333334
          }
        ],
        "labels": [
          "Negative"
        ]
      },
      {
        "framesCount": 3964,
        "duration": 132.133,
        "sequence": [
          {
            "frame": 360,
            "enabled": true,
            "rotation": 0,
            "x": 23.14062499999981,
            "y": 0.16666666666666669,
            "width": 54.74999999999917,
            "height": 98.49999999999949,
            "time": 12
          },
          {
            "x": 23.14062499999981,
            "y": 0.16666666666666669,
            "width": 54.74999999999917,
            "height": 98.49999999999949,
            "rotation": 0,
            "enabled": false,
            "frame": 439,
            "time": 14.633333333333333
          },
          {
            "x": 23.14062499999981,
            "y": 0.16666666666666669,
            "width": 54.74999999999917,
            "height": 98.49999999999949,
            "rotation": 0,
            "enabled": true,
            "frame": 572,
            "time": 19.066666666666666
          },
          {
            "x": 23.14062499999981,
            "y": 0.16666666666666669,
            "width": 54.74999999999917,
            "height": 98.49999999999949,
            "rotation": 0,
            "enabled": false,
            "frame": 675,
            "time": 22.5
          },
          {
            "x": 23.14062499999981,
            "y": 0.16666666666666669,
            "width": 54.74999999999917,
            "height": 98.49999999999949,
            "rotation": 0,
            "enabled": true,
            "frame": 771,
            "time": 25.7
          },
          {
            "x": 23.14062499999981,
            "y": 0.16666666666666669,
            "width": 54.74999999999917,
            "height": 98.49999999999949,
            "rotation": 0,
            "enabled": false,
            "frame": 833,
            "time": 27.766666666666666
          },
          {
            "x": 23.14062499999981,
            "y": 0.16666666666666669,
            "width": 54.74999999999917,
            "height": 98.49999999999949,
            "rotation": 0,
            "enabled": true,
            "frame": 993,
            "time": 33.1
          },
          {
            "x": 23.14062499999981,
            "y": 0.16666666666666669,
            "width": 54.74999999999917,
            "height": 98.49999999999949,
            "rotation": 0,
            "enabled": false,
            "frame": 1482,
            "time": 49.4
          },
          {
            "x": 23.14062499999981,
            "y": 0.16666666666666669,
            "width": 54.74999999999917,
            "height": 98.49999999999949,
            "rotation": 0,
            "enabled": true,
            "frame": 1603,
            "time": 53.43333333333333
          },
          {
            "x": 23.14062499999981,
            "y": 0.16666666666666669,
            "width": 54.74999999999917,
            "height": 98.49999999999949,
            "rotation": 0,
            "enabled": false,
            "frame": 2091,
            "time": 69.7
          },
          {
            "x": 23.14062499999981,
            "y": 0.16666666666666669,
            "width": 54.74999999999917,
            "height": 98.49999999999949,
            "rotation": 0,
            "enabled": true,
            "frame": 3414,
            "time": 113.8
          },
          {
            "x": 23.14062499999981,
            "y": 0.16666666666666669,
            "width": 54.74999999999917,
            "height": 98.49999999999949,
            "rotation": 0,
            "enabled": false,
            "frame": 3481,
            "time": 116.03333333333333
          },
          {
            "x": 23.14062499999981,
            "y": 0.16666666666666669,
            "width": 54.74999999999917,
            "height": 98.49999999999949,
            "rotation": 0,
            "enabled": true,
            "frame": 3535,
            "time": 117.83333333333333
          },
          {
            "x": 23.14062499999981,
            "y": 0.16666666666666669,
            "width": 54.74999999999917,
            "height": 98.49999999999949,
            "rotation": 0,
            "enabled": false,
            "frame": 3633,
            "time": 121.1
          }
        ],
        "labels": [
          "Positive"
        ]
      }
    ],
    "annotator": 1,
    "annotation_id": 2,
    "created_at": "2024-09-22T16:42:05.339670Z",
    "updated_at": "2024-09-22T16:42:05.339687Z",
    "lead_time": 719.235
  },
  {
    "video": "\/data\/upload\/1\/0c6ff85d-VPI-30.mp4",
    "id": 4,
    "box": [
      {
        "framesCount": 3725,
        "duration": 124.139,
        "sequence": [
          {
            "frame": 1,
            "enabled": true,
            "rotation": 0,
            "x": 22.953124999999886,
            "y": 0.33333333333332715,
            "width": 55.03124999999931,
            "height": 98.66666666666579,
            "time": 0.03333333333333333
          },
          {
            "x": 22.953124999999886,
            "y": 0.33333333333332715,
            "width": 55.03124999999931,
            "height": 98.66666666666579,
            "rotation": 0,
            "enabled": false,
            "frame": 447,
            "time": 14.9
          },
          {
            "x": 22.953124999999886,
            "y": 0.33333333333332715,
            "width": 55.03124999999931,
            "height": 98.66666666666579,
            "rotation": 0,
            "enabled": true,
            "frame": 511,
            "time": 17.033333333333335
          },
          {
            "x": 22.953124999999886,
            "y": 0.33333333333332715,
            "width": 55.03124999999931,
            "height": 98.66666666666579,
            "rotation": 0,
            "enabled": false,
            "frame": 631,
            "time": 21.033333333333335
          },
          {
            "x": 22.953124999999886,
            "y": 0.33333333333332715,
            "width": 55.03124999999931,
            "height": 98.66666666666579,
            "rotation": 0,
            "enabled": true,
            "frame": 724,
            "time": 24.133333333333333
          },
          {
            "x": 22.953124999999886,
            "y": 0.33333333333332715,
            "width": 55.03124999999931,
            "height": 98.66666666666579,
            "rotation": 0,
            "enabled": false,
            "frame": 799,
            "time": 26.633333333333333
          },
          {
            "x": 22.953124999999886,
            "y": 0.33333333333332715,
            "width": 55.03124999999931,
            "height": 98.66666666666579,
            "rotation": 0,
            "enabled": true,
            "frame": 896,
            "time": 29.866666666666667
          },
          {
            "x": 22.953124999999886,
            "y": 0.33333333333332715,
            "width": 55.03124999999931,
            "height": 98.66666666666579,
            "rotation": 0,
            "enabled": false,
            "frame": 984,
            "time": 32.8
          },
          {
            "x": 22.953124999999886,
            "y": 0.33333333333332715,
            "width": 55.03124999999931,
            "height": 98.66666666666579,
            "rotation": 0,
            "enabled": true,
            "frame": 1047,
            "time": 34.9
          },
          {
            "x": 22.953124999999886,
            "y": 0.33333333333332715,
            "width": 55.03124999999931,
            "height": 98.66666666666579,
            "rotation": 0,
            "enabled": true,
            "frame": 1132,
            "time": 37.733333333333334
          },
          {
            "x": 22.953124999999886,
            "y": 0.33333333333332715,
            "width": 55.03124999999931,
            "height": 98.66666666666579,
            "rotation": 0,
            "enabled": true,
            "frame": 1192,
            "time": 39.733333333333334
          },
          {
            "x": 22.953124999999886,
            "y": 0.33333333333332715,
            "width": 55.03124999999931,
            "height": 98.66666666666579,
            "rotation": 0,
            "enabled": false,
            "frame": 1304,
            "time": 43.46666666666667
          },
          {
            "x": 22.953124999999886,
            "y": 0.33333333333332715,
            "width": 55.03124999999931,
            "height": 98.66666666666579,
            "rotation": 0,
            "enabled": true,
            "frame": 1348,
            "time": 44.93333333333333
          },
          {
            "x": 22.953124999999886,
            "y": 0.33333333333332715,
            "width": 55.03124999999931,
            "height": 98.66666666666579,
            "rotation": 0,
            "enabled": true,
            "frame": 2121,
            "time": 70.7
          },
          {
            "x": 22.953124999999886,
            "y": 0.33333333333332715,
            "width": 55.03124999999931,
            "height": 98.66666666666579,
            "rotation": 0,
            "enabled": false,
            "frame": 2433,
            "time": 81.1
          },
          {
            "x": 22.953124999999886,
            "y": 0.33333333333332715,
            "width": 55.03124999999931,
            "height": 98.66666666666579,
            "rotation": 0,
            "enabled": true,
            "frame": 2458,
            "time": 81.93333333333334
          },
          {
            "x": 22.953124999999886,
            "y": 0.33333333333332715,
            "width": 55.03124999999931,
            "height": 98.66666666666579,
            "rotation": 0,
            "enabled": false,
            "frame": 2510,
            "time": 83.66666666666667
          },
          {
            "x": 22.953124999999886,
            "y": 0.33333333333332715,
            "width": 55.03124999999931,
            "height": 98.66666666666579,
            "rotation": 0,
            "enabled": true,
            "frame": 2546,
            "time": 84.86666666666666
          },
          {
            "x": 22.953124999999886,
            "y": 0.33333333333332715,
            "width": 55.03124999999931,
            "height": 98.66666666666579,
            "rotation": 0,
            "enabled": false,
            "frame": 2589,
            "time": 86.3
          },
          {
            "x": 22.953124999999886,
            "y": 0.33333333333332715,
            "width": 55.03124999999931,
            "height": 98.66666666666579,
            "rotation": 0,
            "enabled": true,
            "frame": 2611,
            "time": 87.03333333333333
          },
          {
            "x": 22.953124999999886,
            "y": 0.33333333333332715,
            "width": 55.03124999999931,
            "height": 98.66666666666579,
            "rotation": 0,
            "enabled": true,
            "frame": 2771,
            "time": 92.36666666666666
          },
          {
            "x": 22.953124999999886,
            "y": 0.33333333333332715,
            "width": 55.03124999999931,
            "height": 98.66666666666579,
            "rotation": 0,
            "enabled": false,
            "frame": 2979,
            "time": 99.3
          },
          {
            "x": 22.953124999999886,
            "y": 0.33333333333332715,
            "width": 55.03124999999931,
            "height": 98.66666666666579,
            "rotation": 0,
            "enabled": true,
            "frame": 3000,
            "time": 100
          },
          {
            "x": 22.953124999999886,
            "y": 0.33333333333332715,
            "width": 55.03124999999931,
            "height": 98.66666666666579,
            "rotation": 0,
            "enabled": false,
            "frame": 3045,
            "time": 101.5
          },
          {
            "x": 22.953124999999886,
            "y": 0.33333333333332715,
            "width": 55.03124999999931,
            "height": 98.66666666666579,
            "rotation": 0,
            "enabled": true,
            "frame": 3075,
            "time": 102.5
          },
          {
            "x": 22.953124999999886,
            "y": 0.33333333333332715,
            "width": 55.03124999999931,
            "height": 98.66666666666579,
            "rotation": 0,
            "enabled": false,
            "frame": 3119,
            "time": 103.96666666666667
          },
          {
            "x": 22.953124999999886,
            "y": 0.33333333333332715,
            "width": 55.03124999999931,
            "height": 98.66666666666579,
            "rotation": 0,
            "enabled": true,
            "frame": 3163,
            "time": 105.43333333333334
          },
          {
            "x": 22.953124999999886,
            "y": 0.33333333333332715,
            "width": 55.03124999999931,
            "height": 98.66666666666579,
            "rotation": 0,
            "enabled": false,
            "frame": 3401,
            "time": 113.36666666666666
          },
          {
            "x": 22.953124999999886,
            "y": 0.33333333333332715,
            "width": 55.03124999999931,
            "height": 98.66666666666579,
            "rotation": 0,
            "enabled": true,
            "frame": 3436,
            "time": 114.53333333333333
          },
          {
            "x": 22.953124999999886,
            "y": 0.33333333333332715,
            "width": 55.03124999999931,
            "height": 98.66666666666579,
            "rotation": 0,
            "enabled": false,
            "frame": 3535,
            "time": 117.83333333333333
          },
          {
            "x": 22.953124999999886,
            "y": 0.33333333333332715,
            "width": 55.03124999999931,
            "height": 98.66666666666579,
            "rotation": 0,
            "enabled": true,
            "frame": 3547,
            "time": 118.23333333333333
          }
        ],
        "labels": [
          "Negative"
        ]
      },
      {
        "framesCount": 3725,
        "duration": 124.139,
        "sequence": [
          {
            "frame": 448,
            "enabled": true,
            "rotation": 0,
            "x": 23.14062499999982,
            "y": 0.3333333333333269,
            "width": 54.656249999999304,
            "height": 98.66666666666606,
            "time": 14.933333333333334
          },
          {
            "x": 23.14062499999982,
            "y": 0.3333333333333269,
            "width": 54.656249999999304,
            "height": 98.66666666666606,
            "rotation": 0,
            "enabled": false,
            "frame": 510,
            "time": 17
          },
          {
            "x": 23.14062499999982,
            "y": 0.3333333333333269,
            "width": 54.656249999999304,
            "height": 98.66666666666606,
            "rotation": 0,
            "enabled": true,
            "frame": 632,
            "time": 21.066666666666666
          },
          {
            "x": 23.14062499999982,
            "y": 0.3333333333333269,
            "width": 54.656249999999304,
            "height": 98.66666666666606,
            "rotation": 0,
            "enabled": false,
            "frame": 723,
            "time": 24.1
          },
          {
            "x": 23.14062499999982,
            "y": 0.3333333333333269,
            "width": 54.656249999999304,
            "height": 98.66666666666606,
            "rotation": 0,
            "enabled": true,
            "frame": 800,
            "time": 26.666666666666668
          },
          {
            "x": 23.14062499999982,
            "y": 0.3333333333333269,
            "width": 54.656249999999304,
            "height": 98.66666666666606,
            "rotation": 0,
            "enabled": false,
            "frame": 895,
            "time": 29.833333333333332
          },
          {
            "x": 23.14062499999982,
            "y": 0.3333333333333269,
            "width": 54.656249999999304,
            "height": 98.66666666666606,
            "rotation": 0,
            "enabled": true,
            "frame": 985,
            "time": 32.833333333333336
          },
          {
            "x": 23.14062499999982,
            "y": 0.3333333333333269,
            "width": 54.656249999999304,
            "height": 98.66666666666606,
            "rotation": 0,
            "enabled": false,
            "frame": 1046,
            "time": 34.86666666666667
          },
          {
            "x": 23.14062499999982,
            "y": 0.3333333333333269,
            "width": 54.656249999999304,
            "height": 98.66666666666606,
            "rotation": 0,
            "enabled": false,
            "frame": 1191,
            "time": 39.7
          },
          {
            "x": 23.14062499999982,
            "y": 0.3333333333333269,
            "width": 54.656249999999304,
            "height": 98.66666666666606,
            "rotation": 0,
            "enabled": true,
            "frame": 1305,
            "time": 43.5
          },
          {
            "x": 23.14062499999982,
            "y": 0.3333333333333269,
            "width": 54.656249999999304,
            "height": 98.66666666666606,
            "rotation": 0,
            "enabled": false,
            "frame": 1347,
            "time": 44.9
          },
          {
            "x": 23.14062499999982,
            "y": 0.3333333333333269,
            "width": 54.656249999999304,
            "height": 98.66666666666606,
            "rotation": 0,
            "enabled": true,
            "frame": 2434,
            "time": 81.13333333333334
          },
          {
            "x": 23.14062499999982,
            "y": 0.3333333333333269,
            "width": 54.656249999999304,
            "height": 98.66666666666606,
            "rotation": 0,
            "enabled": false,
            "frame": 2456,
            "time": 81.86666666666666
          },
          {
            "x": 23.14062499999982,
            "y": 0.3333333333333269,
            "width": 54.656249999999304,
            "height": 98.66666666666606,
            "rotation": 0,
            "enabled": true,
            "frame": 2511,
            "time": 83.7
          },
          {
            "x": 23.14062499999982,
            "y": 0.3333333333333269,
            "width": 54.656249999999304,
            "height": 98.66666666666606,
            "rotation": 0,
            "enabled": false,
            "frame": 2545,
            "time": 84.83333333333333
          },
          {
            "x": 23.14062499999982,
            "y": 0.3333333333333269,
            "width": 54.656249999999304,
            "height": 98.66666666666606,
            "rotation": 0,
            "enabled": true,
            "frame": 2590,
            "time": 86.33333333333333
          },
          {
            "x": 23.14062499999982,
            "y": 0.3333333333333269,
            "width": 54.656249999999304,
            "height": 98.66666666666606,
            "rotation": 0,
            "enabled": false,
            "frame": 2610,
            "time": 87
          },
          {
            "x": 23.14062499999982,
            "y": 0.3333333333333269,
            "width": 54.656249999999304,
            "height": 98.66666666666606,
            "rotation": 0,
            "enabled": true,
            "frame": 2980,
            "time": 99.33333333333333
          },
          {
            "x": 23.14062499999982,
            "y": 0.3333333333333269,
            "width": 54.656249999999304,
            "height": 98.66666666666606,
            "rotation": 0,
            "enabled": false,
            "frame": 2999,
            "time": 99.96666666666667
          },
          {
            "x": 23.14062499999982,
            "y": 0.3333333333333269,
            "width": 54.656249999999304,
            "height": 98.66666666666606,
            "rotation": 0,
            "enabled": true,
            "frame": 3046,
            "time": 101.53333333333333
          },
          {
            "x": 23.14062499999982,
            "y": 0.3333333333333269,
            "width": 54.656249999999304,
            "height": 98.66666666666606,
            "rotation": 0,
            "enabled": false,
            "frame": 3074,
            "time": 102.46666666666667
          },
          {
            "x": 23.14062499999982,
            "y": 0.3333333333333269,
            "width": 54.656249999999304,
            "height": 98.66666666666606,
            "rotation": 0,
            "enabled": true,
            "frame": 3120,
            "time": 104
          },
          {
            "x": 23.14062499999982,
            "y": 0.3333333333333269,
            "width": 54.656249999999304,
            "height": 98.66666666666606,
            "rotation": 0,
            "enabled": false,
            "frame": 3162,
            "time": 105.4
          },
          {
            "x": 23.14062499999982,
            "y": 0.3333333333333269,
            "width": 54.656249999999304,
            "height": 98.66666666666606,
            "rotation": 0,
            "enabled": true,
            "frame": 3403,
            "time": 113.43333333333334
          },
          {
            "x": 23.14062499999982,
            "y": 0.3333333333333269,
            "width": 54.656249999999304,
            "height": 98.66666666666606,
            "rotation": 0,
            "enabled": false,
            "frame": 3435,
            "time": 114.5
          },
          {
            "x": 23.14062499999982,
            "y": 0.3333333333333269,
            "width": 54.656249999999304,
            "height": 98.66666666666606,
            "rotation": 0,
            "enabled": true,
            "frame": 3536,
            "time": 117.86666666666666
          },
          {
            "x": 23.14062499999982,
            "y": 0.3333333333333269,
            "width": 54.656249999999304,
            "height": 98.66666666666606,
            "rotation": 0,
            "enabled": false,
            "frame": 3546,
            "time": 118.2
          }
        ],
        "labels": [
          "Positive"
        ]
      }
    ],
    "annotator": 1,
    "annotation_id": 3,
    "created_at": "2024-09-22T17:00:58.072249Z",
    "updated_at": "2024-09-22T17:00:58.072272Z",
    "lead_time": 1041.795
  },
  {
    "video": "\/data\/upload\/1\/f319a706-VPI-31.mp4",
    "id": 5,
    "box": [
      {
        "framesCount": 6899,
        "duration": 229.942,
        "sequence": [
          {
            "frame": 1,
            "enabled": true,
            "rotation": 0,
            "x": 23.140624999999485,
            "y": 0.16666666666666247,
            "width": 54.84374999999897,
            "height": 99.1666666666651,
            "time": 0.03333333333333333
          },
          {
            "x": 23.140624999999485,
            "y": 0.16666666666666247,
            "width": 54.84374999999897,
            "height": 99.1666666666651,
            "rotation": 0,
            "enabled": false,
            "frame": 526,
            "time": 17.533333333333335
          },
          {
            "x": 23.140624999999485,
            "y": 0.16666666666666247,
            "width": 54.84374999999897,
            "height": 99.1666666666651,
            "rotation": 0,
            "enabled": true,
            "frame": 589,
            "time": 19.633333333333333
          },
          {
            "x": 23.140624999999485,
            "y": 0.16666666666666247,
            "width": 54.84374999999897,
            "height": 99.1666666666651,
            "rotation": 0,
            "enabled": false,
            "frame": 682,
            "time": 22.733333333333334
          },
          {
            "x": 23.140624999999485,
            "y": 0.16666666666666247,
            "width": 54.84374999999897,
            "height": 99.1666666666651,
            "rotation": 0,
            "enabled": true,
            "frame": 783,
            "time": 26.1
          },
          {
            "x": 23.140624999999485,
            "y": 0.16666666666666247,
            "width": 54.84374999999897,
            "height": 99.1666666666651,
            "rotation": 0,
            "enabled": false,
            "frame": 859,
            "time": 28.633333333333333
          },
          {
            "x": 23.140624999999485,
            "y": 0.16666666666666247,
            "width": 54.84374999999897,
            "height": 99.1666666666651,
            "rotation": 0,
            "enabled": true,
            "frame": 946,
            "time": 31.533333333333335
          },
          {
            "x": 23.140624999999485,
            "y": 0.16666666666666247,
            "width": 54.84374999999897,
            "height": 99.1666666666651,
            "rotation": 0,
            "enabled": false,
            "frame": 1004,
            "time": 33.46666666666667
          },
          {
            "x": 23.140624999999485,
            "y": 0.16666666666666247,
            "width": 54.84374999999897,
            "height": 99.1666666666651,
            "rotation": 0,
            "enabled": true,
            "frame": 1051,
            "time": 35.03333333333333
          },
          {
            "x": 23.140624999999485,
            "y": 0.16666666666666247,
            "width": 54.84374999999897,
            "height": 99.1666666666651,
            "rotation": 0,
            "enabled": false,
            "frame": 1383,
            "time": 46.1
          },
          {
            "x": 23.140624999999485,
            "y": 0.16666666666666247,
            "width": 54.84374999999897,
            "height": 99.1666666666651,
            "rotation": 0,
            "enabled": true,
            "frame": 1677,
            "time": 55.9
          },
          {
            "x": 23.140624999999485,
            "y": 0.16666666666666247,
            "width": 54.84374999999897,
            "height": 99.1666666666651,
            "rotation": 0,
            "enabled": false,
            "frame": 1857,
            "time": 61.9
          },
          {
            "x": 23.140624999999485,
            "y": 0.16666666666666247,
            "width": 54.84374999999897,
            "height": 99.1666666666651,
            "rotation": 0,
            "enabled": true,
            "frame": 1977,
            "time": 65.9
          },
          {
            "x": 23.140624999999485,
            "y": 0.16666666666666247,
            "width": 54.84374999999897,
            "height": 99.1666666666651,
            "rotation": 0,
            "enabled": false,
            "frame": 3259,
            "time": 108.63333333333334
          },
          {
            "x": 23.140624999999485,
            "y": 0.16666666666666247,
            "width": 54.84374999999897,
            "height": 99.1666666666651,
            "rotation": 0,
            "enabled": true,
            "frame": 3487,
            "time": 116.23333333333333
          },
          {
            "x": 23.140624999999485,
            "y": 0.16666666666666247,
            "width": 54.84374999999897,
            "height": 99.1666666666651,
            "rotation": 0,
            "enabled": false,
            "frame": 3726,
            "time": 124.2
          },
          {
            "x": 23.140624999999485,
            "y": 0.16666666666666247,
            "width": 54.84374999999897,
            "height": 99.1666666666651,
            "rotation": 0,
            "enabled": true,
            "frame": 3970,
            "time": 132.33333333333334
          },
          {
            "x": 23.140624999999485,
            "y": 0.16666666666666247,
            "width": 54.84374999999897,
            "height": 99.1666666666651,
            "rotation": 0,
            "enabled": false,
            "frame": 4251,
            "time": 141.7
          },
          {
            "x": 23.140624999999485,
            "y": 0.16666666666666247,
            "width": 54.84374999999897,
            "height": 99.1666666666651,
            "rotation": 0,
            "enabled": true,
            "frame": 4541,
            "time": 151.36666666666667
          },
          {
            "x": 23.140624999999485,
            "y": 0.16666666666666247,
            "width": 54.84374999999897,
            "height": 99.1666666666651,
            "rotation": 0,
            "enabled": false,
            "frame": 4853,
            "time": 161.76666666666668
          },
          {
            "x": 23.140624999999485,
            "y": 0.16666666666666247,
            "width": 54.84374999999897,
            "height": 99.1666666666651,
            "rotation": 0,
            "enabled": true,
            "frame": 5182,
            "time": 172.73333333333332
          },
          {
            "x": 23.140624999999485,
            "y": 0.16666666666666247,
            "width": 54.84374999999897,
            "height": 99.1666666666651,
            "rotation": 0,
            "enabled": false,
            "frame": 5325,
            "time": 177.5
          },
          {
            "x": 23.140624999999485,
            "y": 0.16666666666666247,
            "width": 54.84374999999897,
            "height": 99.1666666666651,
            "rotation": 0,
            "enabled": true,
            "frame": 5454,
            "time": 181.8
          },
          {
            "x": 23.140624999999485,
            "y": 0.16666666666666247,
            "width": 54.84374999999897,
            "height": 99.1666666666651,
            "rotation": 0,
            "enabled": false,
            "frame": 5540,
            "time": 184.66666666666666
          },
          {
            "x": 23.140624999999485,
            "y": 0.16666666666666247,
            "width": 54.84374999999897,
            "height": 99.1666666666651,
            "rotation": 0,
            "enabled": true,
            "frame": 5770,
            "time": 192.33333333333334
          },
          {
            "x": 23.140624999999485,
            "y": 0.16666666666666247,
            "width": 54.84374999999897,
            "height": 99.1666666666651,
            "rotation": 0,
            "enabled": false,
            "frame": 5822,
            "time": 194.06666666666666
          },
          {
            "x": 23.140624999999485,
            "y": 0.16666666666666247,
            "width": 54.84374999999897,
            "height": 99.1666666666651,
            "rotation": 0,
            "enabled": true,
            "frame": 5932,
            "time": 197.73333333333332
          },
          {
            "x": 23.140624999999485,
            "y": 0.16666666666666247,
            "width": 54.84374999999897,
            "height": 99.1666666666651,
            "rotation": 0,
            "enabled": false,
            "frame": 6106,
            "time": 203.53333333333333
          },
          {
            "x": 23.140624999999485,
            "y": 0.16666666666666247,
            "width": 54.84374999999897,
            "height": 99.1666666666651,
            "rotation": 0,
            "enabled": true,
            "frame": 6181,
            "time": 206.03333333333333
          },
          {
            "x": 23.140624999999485,
            "y": 0.16666666666666247,
            "width": 54.84374999999897,
            "height": 99.1666666666651,
            "rotation": 0,
            "enabled": false,
            "frame": 6260,
            "time": 208.66666666666666
          },
          {
            "x": 23.140624999999485,
            "y": 0.16666666666666247,
            "width": 54.84374999999897,
            "height": 99.1666666666651,
            "rotation": 0,
            "enabled": true,
            "frame": 6335,
            "time": 211.16666666666666
          },
          {
            "x": 23.140624999999485,
            "y": 0.16666666666666247,
            "width": 54.84374999999897,
            "height": 99.1666666666651,
            "rotation": 0,
            "enabled": false,
            "frame": 6394,
            "time": 213.13333333333333
          },
          {
            "x": 23.140624999999485,
            "y": 0.16666666666666247,
            "width": 54.84374999999897,
            "height": 99.1666666666651,
            "rotation": 0,
            "enabled": true,
            "frame": 6446,
            "time": 214.86666666666667
          },
          {
            "x": 23.140624999999485,
            "y": 0.16666666666666247,
            "width": 54.84374999999897,
            "height": 99.1666666666651,
            "rotation": 0,
            "enabled": false,
            "frame": 6516,
            "time": 217.2
          },
          {
            "x": 23.140624999999485,
            "y": 0.16666666666666247,
            "width": 54.84374999999897,
            "height": 99.1666666666651,
            "rotation": 0,
            "enabled": true,
            "frame": 6630,
            "time": 221
          },
          {
            "x": 23.140624999999485,
            "y": 0.16666666666666247,
            "width": 54.84374999999897,
            "height": 99.1666666666651,
            "rotation": 0,
            "enabled": false,
            "frame": 6687,
            "time": 222.9
          },
          {
            "x": 23.140624999999485,
            "y": 0.16666666666666247,
            "width": 54.84374999999897,
            "height": 99.1666666666651,
            "rotation": 0,
            "enabled": true,
            "frame": 6738,
            "time": 224.6
          }
        ],
        "labels": [
          "Negative"
        ]
      },
      {
        "framesCount": 6899,
        "duration": 229.942,
        "sequence": [
          {
            "frame": 527,
            "enabled": true,
            "rotation": 0,
            "x": 23.046874999999705,
            "y": 0.16666666666665597,
            "width": 54.84374999999976,
            "height": 98.66666666666568,
            "time": 17.566666666666666
          },
          {
            "x": 23.046874999999705,
            "y": 0.16666666666665597,
            "width": 54.84374999999976,
            "height": 98.66666666666568,
            "rotation": 0,
            "enabled": false,
            "frame": 588,
            "time": 19.6
          },
          {
            "x": 23.046874999999705,
            "y": 0.16666666666665597,
            "width": 54.84374999999976,
            "height": 98.66666666666568,
            "rotation": 0,
            "enabled": true,
            "frame": 683,
            "time": 22.766666666666666
          },
          {
            "x": 23.046874999999705,
            "y": 0.16666666666665597,
            "width": 54.84374999999976,
            "height": 98.66666666666568,
            "rotation": 0,
            "enabled": false,
            "frame": 782,
            "time": 26.066666666666666
          },
          {
            "x": 23.046874999999705,
            "y": 0.16666666666665597,
            "width": 54.84374999999976,
            "height": 98.66666666666568,
            "rotation": 0,
            "enabled": true,
            "frame": 860,
            "time": 28.666666666666668
          },
          {
            "x": 23.046874999999705,
            "y": 0.16666666666665597,
            "width": 54.84374999999976,
            "height": 98.66666666666568,
            "rotation": 0,
            "enabled": false,
            "frame": 945,
            "time": 31.5
          },
          {
            "x": 23.046874999999705,
            "y": 0.16666666666665597,
            "width": 54.84374999999976,
            "height": 98.66666666666568,
            "rotation": 0,
            "enabled": true,
            "frame": 1005,
            "time": 33.5
          },
          {
            "x": 23.046874999999705,
            "y": 0.16666666666665597,
            "width": 54.84374999999976,
            "height": 98.66666666666568,
            "rotation": 0,
            "enabled": false,
            "frame": 1050,
            "time": 35
          },
          {
            "x": 23.046874999999705,
            "y": 0.16666666666665597,
            "width": 54.84374999999976,
            "height": 98.66666666666568,
            "rotation": 0,
            "enabled": true,
            "frame": 1384,
            "time": 46.13333333333333
          },
          {
            "x": 23.046874999999705,
            "y": 0.16666666666665597,
            "width": 54.84374999999976,
            "height": 98.66666666666568,
            "rotation": 0,
            "enabled": false,
            "frame": 1676,
            "time": 55.86666666666667
          },
          {
            "x": 23.046874999999705,
            "y": 0.16666666666665597,
            "width": 54.84374999999976,
            "height": 98.66666666666568,
            "rotation": 0,
            "enabled": true,
            "frame": 1858,
            "time": 61.93333333333333
          },
          {
            "x": 23.046874999999705,
            "y": 0.16666666666665597,
            "width": 54.84374999999976,
            "height": 98.66666666666568,
            "rotation": 0,
            "enabled": false,
            "frame": 1976,
            "time": 65.86666666666666
          },
          {
            "x": 23.046874999999705,
            "y": 0.16666666666665597,
            "width": 54.84374999999976,
            "height": 98.66666666666568,
            "rotation": 0,
            "enabled": true,
            "frame": 3260,
            "time": 108.66666666666667
          },
          {
            "x": 23.046874999999705,
            "y": 0.16666666666665597,
            "width": 54.84374999999976,
            "height": 98.66666666666568,
            "rotation": 0,
            "enabled": false,
            "frame": 3486,
            "time": 116.2
          },
          {
            "x": 23.046874999999705,
            "y": 0.16666666666665597,
            "width": 54.84374999999976,
            "height": 98.66666666666568,
            "rotation": 0,
            "enabled": true,
            "frame": 3727,
            "time": 124.23333333333333
          },
          {
            "x": 23.046874999999705,
            "y": 0.16666666666665597,
            "width": 54.84374999999976,
            "height": 98.66666666666568,
            "rotation": 0,
            "enabled": false,
            "frame": 3969,
            "time": 132.3
          },
          {
            "x": 23.046874999999705,
            "y": 0.16666666666665597,
            "width": 54.84374999999976,
            "height": 98.66666666666568,
            "rotation": 0,
            "enabled": true,
            "frame": 4252,
            "time": 141.73333333333332
          },
          {
            "x": 23.046874999999705,
            "y": 0.16666666666665597,
            "width": 54.84374999999976,
            "height": 98.66666666666568,
            "rotation": 0,
            "enabled": false,
            "frame": 4540,
            "time": 151.33333333333334
          },
          {
            "x": 23.046874999999705,
            "y": 0.16666666666665597,
            "width": 54.84374999999976,
            "height": 98.66666666666568,
            "rotation": 0,
            "enabled": true,
            "frame": 4854,
            "time": 161.8
          },
          {
            "x": 23.046874999999705,
            "y": 0.16666666666665597,
            "width": 54.84374999999976,
            "height": 98.66666666666568,
            "rotation": 0,
            "enabled": false,
            "frame": 5181,
            "time": 172.7
          },
          {
            "x": 23.046874999999705,
            "y": 0.16666666666665597,
            "width": 54.84374999999976,
            "height": 98.66666666666568,
            "rotation": 0,
            "enabled": true,
            "frame": 5326,
            "time": 177.53333333333333
          },
          {
            "x": 23.046874999999705,
            "y": 0.16666666666665597,
            "width": 54.84374999999976,
            "height": 98.66666666666568,
            "rotation": 0,
            "enabled": false,
            "frame": 5453,
            "time": 181.76666666666668
          },
          {
            "x": 23.046874999999705,
            "y": 0.16666666666665597,
            "width": 54.84374999999976,
            "height": 98.66666666666568,
            "rotation": 0,
            "enabled": true,
            "frame": 5541,
            "time": 184.7
          },
          {
            "x": 23.046874999999705,
            "y": 0.16666666666665597,
            "width": 54.84374999999976,
            "height": 98.66666666666568,
            "rotation": 0,
            "enabled": false,
            "frame": 5769,
            "time": 192.3
          },
          {
            "x": 23.046874999999705,
            "y": 0.16666666666665597,
            "width": 54.84374999999976,
            "height": 98.66666666666568,
            "rotation": 0,
            "enabled": true,
            "frame": 5823,
            "time": 194.1
          },
          {
            "x": 23.046874999999705,
            "y": 0.16666666666665597,
            "width": 54.84374999999976,
            "height": 98.66666666666568,
            "rotation": 0,
            "enabled": false,
            "frame": 5931,
            "time": 197.7
          },
          {
            "x": 23.046874999999705,
            "y": 0.16666666666665597,
            "width": 54.84374999999976,
            "height": 98.66666666666568,
            "rotation": 0,
            "enabled": true,
            "frame": 6107,
            "time": 203.56666666666666
          },
          {
            "x": 23.046874999999705,
            "y": 0.16666666666665597,
            "width": 54.84374999999976,
            "height": 98.66666666666568,
            "rotation": 0,
            "enabled": false,
            "frame": 6180,
            "time": 206
          },
          {
            "x": 23.046874999999705,
            "y": 0.16666666666665597,
            "width": 54.84374999999976,
            "height": 98.66666666666568,
            "rotation": 0,
            "enabled": true,
            "frame": 6261,
            "time": 208.7
          },
          {
            "x": 23.046874999999705,
            "y": 0.16666666666665597,
            "width": 54.84374999999976,
            "height": 98.66666666666568,
            "rotation": 0,
            "enabled": false,
            "frame": 6334,
            "time": 211.13333333333333
          },
          {
            "x": 23.046874999999705,
            "y": 0.16666666666665597,
            "width": 54.84374999999976,
            "height": 98.66666666666568,
            "rotation": 0,
            "enabled": true,
            "frame": 6395,
            "time": 213.16666666666666
          },
          {
            "x": 23.046874999999705,
            "y": 0.16666666666665597,
            "width": 54.84374999999976,
            "height": 98.66666666666568,
            "rotation": 0,
            "enabled": false,
            "frame": 6445,
            "time": 214.83333333333334
          },
          {
            "x": 23.046874999999705,
            "y": 0.16666666666665597,
            "width": 54.84374999999976,
            "height": 98.66666666666568,
            "rotation": 0,
            "enabled": true,
            "frame": 6517,
            "time": 217.23333333333332
          },
          {
            "x": 23.046874999999705,
            "y": 0.16666666666665597,
            "width": 54.84374999999976,
            "height": 98.66666666666568,
            "rotation": 0,
            "enabled": false,
            "frame": 6629,
            "time": 220.96666666666667
          },
          {
            "x": 23.046874999999705,
            "y": 0.16666666666665597,
            "width": 54.84374999999976,
            "height": 98.66666666666568,
            "rotation": 0,
            "enabled": true,
            "frame": 6688,
            "time": 222.93333333333334
          },
          {
            "x": 23.046874999999705,
            "y": 0.16666666666665597,
            "width": 54.84374999999976,
            "height": 98.66666666666568,
            "rotation": 0,
            "enabled": false,
            "frame": 6737,
            "time": 224.56666666666666
          }
        ],
        "labels": [
          "Positive"
        ]
      }
    ],
    "annotator": 1,
    "annotation_id": 4,
    "created_at": "2024-09-22T17:25:09.921561Z",
    "updated_at": "2024-09-22T17:25:09.921575Z",
    "lead_time": 1412.677
  },
  {
    "video": "\/data\/upload\/1\/ae173107-VPI-33.mp4",
    "id": 6,
    "box": [
      {
        "framesCount": 5674,
        "duration": 189.104,
        "sequence": [
          {
            "frame": 1,
            "enabled": true,
            "rotation": 0,
            "x": 23.140624999999567,
            "y": 0.16666666666665564,
            "width": 54.74999999999955,
            "height": 98.83333333333186,
            "time": 0.03333333333333333
          },
          {
            "x": 23.140624999999567,
            "y": 0.16666666666665564,
            "width": 54.74999999999955,
            "height": 98.83333333333186,
            "rotation": 0,
            "enabled": false,
            "frame": 382,
            "time": 12.733333333333333
          },
          {
            "x": 23.140624999999567,
            "y": 0.16666666666665564,
            "width": 54.74999999999955,
            "height": 98.83333333333186,
            "rotation": 0,
            "enabled": true,
            "frame": 453,
            "time": 15.1
          },
          {
            "x": 23.140624999999567,
            "y": 0.16666666666665564,
            "width": 54.74999999999955,
            "height": 98.83333333333186,
            "rotation": 0,
            "enabled": false,
            "frame": 545,
            "time": 18.166666666666668
          },
          {
            "x": 23.140624999999567,
            "y": 0.16666666666665564,
            "width": 54.74999999999955,
            "height": 98.83333333333186,
            "rotation": 0,
            "enabled": true,
            "frame": 676,
            "time": 22.533333333333335
          },
          {
            "x": 23.140624999999567,
            "y": 0.16666666666665564,
            "width": 54.74999999999955,
            "height": 98.83333333333186,
            "rotation": 0,
            "enabled": false,
            "frame": 760,
            "time": 25.333333333333332
          },
          {
            "x": 23.140624999999567,
            "y": 0.16666666666665564,
            "width": 54.74999999999955,
            "height": 98.83333333333186,
            "rotation": 0,
            "enabled": true,
            "frame": 841,
            "time": 28.033333333333335
          },
          {
            "x": 23.140624999999567,
            "y": 0.16666666666665564,
            "width": 54.74999999999955,
            "height": 98.83333333333186,
            "rotation": 0,
            "enabled": false,
            "frame": 923,
            "time": 30.766666666666666
          },
          {
            "x": 23.140624999999567,
            "y": 0.16666666666665564,
            "width": 54.74999999999955,
            "height": 98.83333333333186,
            "rotation": 0,
            "enabled": true,
            "frame": 992,
            "time": 33.06666666666667
          },
          {
            "x": 23.140624999999567,
            "y": 0.16666666666665564,
            "width": 54.74999999999955,
            "height": 98.83333333333186,
            "rotation": 0,
            "enabled": false,
            "frame": 1516,
            "time": 50.53333333333333
          },
          {
            "x": 23.140624999999567,
            "y": 0.16666666666665564,
            "width": 54.74999999999955,
            "height": 98.83333333333186,
            "rotation": 0,
            "enabled": true,
            "frame": 1977,
            "time": 65.9
          },
          {
            "x": 23.140624999999567,
            "y": 0.16666666666665564,
            "width": 54.74999999999955,
            "height": 98.83333333333186,
            "rotation": 0,
            "enabled": false,
            "frame": 2321,
            "time": 77.36666666666666
          },
          {
            "x": 23.140624999999567,
            "y": 0.16666666666665564,
            "width": 54.74999999999955,
            "height": 98.83333333333186,
            "rotation": 0,
            "enabled": true,
            "frame": 2851,
            "time": 95.03333333333333
          },
          {
            "x": 23.140624999999567,
            "y": 0.16666666666665564,
            "width": 54.74999999999955,
            "height": 98.83333333333186,
            "rotation": 0,
            "enabled": false,
            "frame": 3053,
            "time": 101.76666666666667
          },
          {
            "x": 23.140624999999567,
            "y": 0.16666666666665564,
            "width": 54.74999999999955,
            "height": 98.83333333333186,
            "rotation": 0,
            "enabled": true,
            "frame": 3584,
            "time": 119.46666666666667
          },
          {
            "x": 23.140624999999567,
            "y": 0.16666666666665564,
            "width": 54.74999999999955,
            "height": 98.83333333333186,
            "rotation": 0,
            "enabled": false,
            "frame": 3819,
            "time": 127.3
          },
          {
            "x": 23.140624999999567,
            "y": 0.16666666666665564,
            "width": 54.74999999999955,
            "height": 98.83333333333186,
            "rotation": 0,
            "enabled": true,
            "frame": 3900,
            "time": 130
          },
          {
            "x": 23.140624999999567,
            "y": 0.16666666666665564,
            "width": 54.74999999999955,
            "height": 98.83333333333186,
            "rotation": 0,
            "enabled": false,
            "frame": 4022,
            "time": 134.06666666666666
          },
          {
            "x": 23.140624999999567,
            "y": 0.16666666666665564,
            "width": 54.74999999999955,
            "height": 98.83333333333186,
            "rotation": 0,
            "enabled": true,
            "frame": 4083,
            "time": 136.1
          },
          {
            "x": 23.140624999999567,
            "y": 0.16666666666665564,
            "width": 54.74999999999955,
            "height": 98.83333333333186,
            "rotation": 0,
            "enabled": false,
            "frame": 4164,
            "time": 138.8
          },
          {
            "x": 23.140624999999567,
            "y": 0.16666666666665564,
            "width": 54.74999999999955,
            "height": 98.83333333333186,
            "rotation": 0,
            "enabled": true,
            "frame": 4213,
            "time": 140.43333333333334
          },
          {
            "x": 23.140624999999567,
            "y": 0.16666666666665564,
            "width": 54.74999999999955,
            "height": 98.83333333333186,
            "rotation": 0,
            "enabled": false,
            "frame": 4309,
            "time": 143.63333333333333
          },
          {
            "x": 23.140624999999567,
            "y": 0.16666666666665564,
            "width": 54.74999999999955,
            "height": 98.83333333333186,
            "rotation": 0,
            "enabled": true,
            "frame": 4422,
            "time": 147.4
          },
          {
            "x": 23.140624999999567,
            "y": 0.16666666666665564,
            "width": 54.74999999999955,
            "height": 98.83333333333186,
            "rotation": 0,
            "enabled": false,
            "frame": 4579,
            "time": 152.63333333333333
          },
          {
            "x": 23.140624999999567,
            "y": 0.16666666666665564,
            "width": 54.74999999999955,
            "height": 98.83333333333186,
            "rotation": 0,
            "enabled": true,
            "frame": 4673,
            "time": 155.76666666666668
          }
        ],
        "labels": [
          "Negative"
        ]
      },
      {
        "framesCount": 5674,
        "duration": 189.104,
        "sequence": [
          {
            "frame": 383,
            "enabled": true,
            "rotation": 0,
            "x": 23.0468749999997,
            "y": 0.33333333333332765,
            "width": 54.749999999999076,
            "height": 98.83333333333269,
            "time": 12.766666666666667
          },
          {
            "x": 23.0468749999997,
            "y": 0.33333333333332765,
            "width": 54.749999999999076,
            "height": 98.83333333333269,
            "rotation": 0,
            "enabled": false,
            "frame": 452,
            "time": 15.066666666666666
          },
          {
            "x": 23.0468749999997,
            "y": 0.33333333333332765,
            "width": 54.749999999999076,
            "height": 98.83333333333269,
            "rotation": 0,
            "enabled": true,
            "frame": 546,
            "time": 18.2
          },
          {
            "x": 23.0468749999997,
            "y": 0.33333333333332765,
            "width": 54.749999999999076,
            "height": 98.83333333333269,
            "rotation": 0,
            "enabled": false,
            "frame": 675,
            "time": 22.5
          },
          {
            "x": 23.0468749999997,
            "y": 0.33333333333332765,
            "width": 54.749999999999076,
            "height": 98.83333333333269,
            "rotation": 0,
            "enabled": true,
            "frame": 761,
            "time": 25.366666666666667
          },
          {
            "x": 23.0468749999997,
            "y": 0.33333333333332765,
            "width": 54.749999999999076,
            "height": 98.83333333333269,
            "rotation": 0,
            "enabled": false,
            "frame": 840,
            "time": 28
          },
          {
            "x": 23.0468749999997,
            "y": 0.33333333333332765,
            "width": 54.749999999999076,
            "height": 98.83333333333269,
            "rotation": 0,
            "enabled": true,
            "frame": 924,
            "time": 30.8
          },
          {
            "x": 23.0468749999997,
            "y": 0.33333333333332765,
            "width": 54.749999999999076,
            "height": 98.83333333333269,
            "rotation": 0,
            "enabled": false,
            "frame": 991,
            "time": 33.03333333333333
          },
          {
            "x": 23.0468749999997,
            "y": 0.33333333333332765,
            "width": 54.749999999999076,
            "height": 98.83333333333269,
            "rotation": 0,
            "enabled": true,
            "frame": 1517,
            "time": 50.56666666666667
          },
          {
            "x": 23.0468749999997,
            "y": 0.33333333333332765,
            "width": 54.749999999999076,
            "height": 98.83333333333269,
            "rotation": 0,
            "enabled": false,
            "frame": 1976,
            "time": 65.86666666666666
          },
          {
            "x": 23.0468749999997,
            "y": 0.33333333333332765,
            "width": 54.749999999999076,
            "height": 98.83333333333269,
            "rotation": 0,
            "enabled": true,
            "frame": 2322,
            "time": 77.4
          },
          {
            "x": 23.0468749999997,
            "y": 0.33333333333332765,
            "width": 54.749999999999076,
            "height": 98.83333333333269,
            "rotation": 0,
            "enabled": false,
            "frame": 2850,
            "time": 95
          },
          {
            "x": 23.0468749999997,
            "y": 0.33333333333332765,
            "width": 54.749999999999076,
            "height": 98.83333333333269,
            "rotation": 0,
            "enabled": true,
            "frame": 3054,
            "time": 101.8
          },
          {
            "x": 23.0468749999997,
            "y": 0.33333333333332765,
            "width": 54.749999999999076,
            "height": 98.83333333333269,
            "rotation": 0,
            "enabled": false,
            "frame": 3583,
            "time": 119.43333333333334
          },
          {
            "x": 23.0468749999997,
            "y": 0.33333333333332765,
            "width": 54.749999999999076,
            "height": 98.83333333333269,
            "rotation": 0,
            "enabled": true,
            "frame": 3820,
            "time": 127.33333333333333
          },
          {
            "x": 23.0468749999997,
            "y": 0.33333333333332765,
            "width": 54.749999999999076,
            "height": 98.83333333333269,
            "rotation": 0,
            "enabled": false,
            "frame": 3899,
            "time": 129.96666666666667
          },
          {
            "x": 23.0468749999997,
            "y": 0.33333333333332765,
            "width": 54.749999999999076,
            "height": 98.83333333333269,
            "rotation": 0,
            "enabled": true,
            "frame": 4023,
            "time": 134.1
          },
          {
            "x": 23.0468749999997,
            "y": 0.33333333333332765,
            "width": 54.749999999999076,
            "height": 98.83333333333269,
            "rotation": 0,
            "enabled": false,
            "frame": 4082,
            "time": 136.06666666666666
          },
          {
            "x": 23.0468749999997,
            "y": 0.33333333333332765,
            "width": 54.749999999999076,
            "height": 98.83333333333269,
            "rotation": 0,
            "enabled": true,
            "frame": 4165,
            "time": 138.83333333333334
          },
          {
            "x": 23.0468749999997,
            "y": 0.33333333333332765,
            "width": 54.749999999999076,
            "height": 98.83333333333269,
            "rotation": 0,
            "enabled": false,
            "frame": 4212,
            "time": 140.4
          },
          {
            "x": 23.0468749999997,
            "y": 0.33333333333332765,
            "width": 54.749999999999076,
            "height": 98.83333333333269,
            "rotation": 0,
            "enabled": true,
            "frame": 4310,
            "time": 143.66666666666666
          },
          {
            "x": 23.0468749999997,
            "y": 0.33333333333332765,
            "width": 54.749999999999076,
            "height": 98.83333333333269,
            "rotation": 0,
            "enabled": false,
            "frame": 4421,
            "time": 147.36666666666667
          },
          {
            "x": 23.0468749999997,
            "y": 0.33333333333332765,
            "width": 54.749999999999076,
            "height": 98.83333333333269,
            "rotation": 0,
            "enabled": true,
            "frame": 4580,
            "time": 152.66666666666666
          },
          {
            "x": 23.0468749999997,
            "y": 0.33333333333332765,
            "width": 54.749999999999076,
            "height": 98.83333333333269,
            "rotation": 0,
            "enabled": false,
            "frame": 4672,
            "time": 155.73333333333332
          }
        ],
        "labels": [
          "Positive"
        ]
      }
    ],
    "annotator": 1,
    "annotation_id": 5,
    "created_at": "2024-09-22T17:37:00.832619Z",
    "updated_at": "2024-09-22T17:37:00.832634Z",
    "lead_time": 527.423
  }
]